wolfsoftware/github_token_validator/__init__.py
wolfsoftware/github_token_validator/cli.py
wolfsoftware/github_token_validator/config.py
wolfsoftware/github_token_validator/globals.py
wolfsoftware/github_token_validator/main.py
wolfsoftware/github_token_validator/token.py
wolfsoftware.github_token_validator-0.1.3.dist-info/LICENSE.md
wolfsoftware.github_token_validator-0.1.3.dist-info/METADATA
wolfsoftware.github_token_validator-0.1.3.dist-info/WHEEL
wolfsoftware.github_token_validator-0.1.3.dist-info/entry_points.txt
wolfsoftware.github_token_validator-0.1.3.dist-info/top_level.txt
wolfsoftware.github_token_validator-0.1.3.dist-info/RECORD
