Metadata-Version: 2.1
Name: wolfsoftware.github-token-validator
Version: 0.1.3
Summary: A tool to validate GitHub Tokens.
Home-page: https://github.com/GitHubToolbox/github-token-validator
Author: Wolf Software
Author-email: pypi@wolfsoftware.com
Project-URL: Source, https://github.com/GitHubToolbox/github-token-validator
Project-URL: Tracker, https://github.com/GitHubToolbox/github-token-validator/issues/
Project-URL: Documentation, https://github.com/GitHubToolbox/github-token-validator
Project-URL: Sponsor, https://github.com/sponsors/WolfSoftware
Classifier: Environment :: Console
Classifier: Intended Audience :: Developers
Classifier: Programming Language :: Python :: 3
Classifier: License :: OSI Approved :: MIT License
Classifier: Operating System :: OS Independent
Classifier: Topic :: Software Development
Requires-Python: >=3.9
License-File: LICENSE.md
Requires-Dist: prettytable ==3.10.0
Requires-Dist: requests ==2.32.2
Requires-Dist: wolfsoftware.notify ==0.1.0
